LICENSE
fastcrud/__init__.py
fastcrud/fastapi_dependencies.py
fastcrud/py.typed
fastcrud/types.py
fastcrud/core/__init__.py
fastcrud/core/field_management.py
fastcrud/core/introspection.py
fastcrud/core/join_processing.py
fastcrud/core/pagination.py
fastcrud/core/protocols.py
fastcrud/core/config/__init__.py
fastcrud/core/config/crud_configs.py
fastcrud/core/config/join_configs.py
fastcrud/core/data/__init__.py
fastcrud/core/data/formatting.py
fastcrud/core/data/nesting.py
fastcrud/core/data/transforms.py
fastcrud/core/filtering/__init__.py
fastcrud/core/filtering/operators.py
fastcrud/core/filtering/processor.py
fastcrud/core/filtering/validators.py
fastcrud/core/query/__init__.py
fastcrud/core/query/builder.py
fastcrud/core/query/joins.py
fastcrud/core/query/one_to_many.py
fastcrud/core/query/sorting.py
fastcrud/crud/__init__.py
fastcrud/crud/data_preparation.py
fastcrud/crud/database_specific.py
fastcrud/crud/execution.py
fastcrud/crud/fast_crud.py
fastcrud/crud/validation.py
fastcrud/endpoint/__init__.py
fastcrud/endpoint/crud_router.py
fastcrud/endpoint/endpoint_creator.py
fastcrud/examples/article/model.py
fastcrud/examples/article/schemas.py
fastcrud/examples/author/model.py
fastcrud/examples/author/schemas.py
fastcrud/examples/customer/model.py
fastcrud/examples/customer/schemas.py
fastcrud/examples/department/model.py
fastcrud/examples/department/schemas.py
fastcrud/examples/item/model.py
fastcrud/examples/item/schemas.py
fastcrud/examples/item/sqlmodel.py
fastcrud/examples/mymodel/model.py
fastcrud/examples/mymodel/schemas.py
fastcrud/examples/order/model.py
fastcrud/examples/order/schemas.py
fastcrud/examples/product/model.py
fastcrud/examples/product/schemas.py
fastcrud/examples/profile/model.py
fastcrud/examples/profile/schemas.py
fastcrud/examples/story/model.py
fastcrud/examples/story/schemas.py
fastcrud/examples/task/model.py
fastcrud/examples/task/schemas.py
fastcrud/examples/tier/model.py
fastcrud/examples/tier/schemas.py
fastcrud-0.21.0.dist-info/METADATA
fastcrud-0.21.0.dist-info/WHEEL
fastcrud-0.21.0.dist-info/licenses/LICENSE
fastcrud-0.21.0.dist-info/RECORD
