Metadata-Version: 2.4
Name: fastcrud
Version: 0.21.0
Summary: FastCRUD is a Python package for FastAPI, offering robust async CRUD operations and flexible endpoint creation utilities.
Project-URL: Repository, https://github.com/benavlabs/fastcrud
Author-email: Igor Benav <igor@benav.io>
License-Expression: MIT
License-File: LICENSE
Keywords: async,crud,fastapi,pydantic,sqlalchemy
Classifier: Development Status :: 4 - Beta
Classifier: Framework :: FastAPI
Classifier: Intended Audience :: Developers
Classifier: License :: OSI Approved :: MIT License
Classifier: Operating System :: OS Independent
Classifier: Programming Language :: Python :: 3
Classifier: Programming Language :: Python :: 3.10
Classifier: Programming Language :: Python :: 3.11
Classifier: Programming Language :: Python :: 3.12
Classifier: Programming Language :: Python :: 3.13
Classifier: Topic :: Software Development :: Libraries
Classifier: Typing :: Typed
Requires-Python: <4,>=3.10
Requires-Dist: fastapi>=0.100.0
Requires-Dist: pydantic<3,>=2.0.0
Requires-Dist: sqlalchemy-utils<0.42,>=0.41.2
Requires-Dist: sqlalchemy<3,>=2.0.0
